samsara/__init__.py
samsara/addresses/__init__.py
samsara/addresses/client.py
samsara/addresses/raw_client.py
samsara/addresses/types/__init__.py
samsara/addresses/types/create_address_request_address_types_item.py
samsara/addresses/types/update_address_request_address_types_item.py
samsara/alerts/__init__.py
samsara/alerts/client.py
samsara/alerts/configurations/__init__.py
samsara/alerts/configurations/client.py
samsara/alerts/configurations/raw_client.py
samsara/alerts/configurations/types/__init__.py
samsara/alerts/configurations/types/configurations_list_request_status.py
samsara/alerts/incidents/__init__.py
samsara/alerts/incidents/client.py
samsara/alerts/incidents/raw_client.py
samsara/alerts/raw_client.py
samsara/assets/__init__.py
samsara/assets/client.py
samsara/assets/location_and_speed/__init__.py
samsara/assets/location_and_speed/client.py
samsara/assets/location_and_speed/raw_client.py
samsara/assets/raw_client.py
samsara/assets/types/__init__.py
samsara/assets/types/assets_create_asset_request_body_regulation_mode.py
samsara/assets/types/assets_create_asset_request_body_type.py
samsara/assets/types/assets_list_request_type.py
samsara/assets/types/assets_update_asset_request_body_regulation_mode.py
samsara/assets/types/assets_update_asset_request_body_type.py
samsara/attributes/__init__.py
samsara/attributes/client.py
samsara/attributes/raw_client.py
samsara/attributes/types/__init__.py
samsara/attributes/types/attributes_delete_request_entity_type.py
samsara/attributes/types/attributes_get_request_entity_type.py
samsara/attributes/types/attributes_list_request_entity_type.py
samsara/attributes/types/create_attribute_request_attribute_type.py
samsara/attributes/types/create_attribute_request_attribute_value_quantity.py
samsara/attributes/types/create_attribute_request_entity_type.py
samsara/attributes/types/update_attribute_request_attribute_type.py
samsara/attributes/types/update_attribute_request_attribute_value_quantity.py
samsara_api-2.0.2.dist-info/LICENSE
samsara_api-2.0.2.dist-info/METADATA
samsara_api-2.0.2.dist-info/WHEEL
samsara_api-2.0.2.dist-info/RECORD
